dvartk/__init__.py
dvartk/parser.py
dvartk/plotter.py
dvartk/process.py
dvartk-0.1.15.dist-info/LICENSE
dvartk-0.1.15.dist-info/METADATA
dvartk-0.1.15.dist-info/WHEEL
dvartk-0.1.15.dist-info/top_level.txt
dvartk-0.1.15.dist-info/RECORD
