Metadata-Version: 2.1
Name: dvartk
Version: 0.1.15
Home-page: https://github.com/soymintc/dvartk
Author: Seongmin Choi
Author-email: soymintc@gmail.com
License: MIT
Keywords: SNV,SV,comparison,toolkit
License-File: LICENSE
Requires-Dist: pandas
Requires-Dist: wgs-analysis
Requires-Dist: numpy
Requires-Dist: matplotlib
Requires-Dist: matplotlib-venn
Requires-Dist: seaborn
Requires-Dist: SigProfilerMatrixGenerator
